{
    "DataType": "PotData",
    "DataVersion": 0,
    "GameVersion": "0.3.4f8",
    "GUID": "7d423271-b663-470b-b692-754ac3529a87",
    "ItemString": "{\n    \"DataType\": \"ItemData\",\n    \"DataVersion\": 0,\n    \"GameVersion\": \"0.3.4f8\",\n    \"ID\": \"moisturepreservingpot\",\n    \"Quantity\": 1\n}",
    "LoadOrder": 0,
    "GridGUID": "d47666ba-6076-4779-9c8a-ffede5ff83ad",
    "OriginCoordinate": {
        "x": 10.0,
        "y": 6.0
    },
    "Rotation": 90,
    "SoilID": "extralonglifesoil",
    "SoilLevel": 20.0,
    "RemainingSoilUses": 3,
    "WaterLevel": 0.0,
    "AppliedAdditives": [],
    "PlantData": {
        "DataType": "PlantData",
        "DataVersion": 0,
        "GameVersion": "0.3.4f8",
        "SeedID": "",
        "GrowthProgress": 0.0,
        "YieldLevel": 0.0,
        "QualityLevel": 0.0,
        "ActiveBuds": []
    }
}